mongolog/__init__.py
mongolog/handlers.py
mongolog/logger.py
mongolog/tests.py
mongopylogger-2.0.0.dist-info/LICENSE
mongopylogger-2.0.0.dist-info/METADATA
mongopylogger-2.0.0.dist-info/WHEEL
mongopylogger-2.0.0.dist-info/top_level.txt
mongopylogger-2.0.0.dist-info/RECORD
