Metadata-Version: 2.1
Name: mongopylogger
Version: 2.0.0
Summary: Logger for python, with MongoHandler.
Home-page: UNKNOWN
Author: 
Author-email: 
License: MIT
Keywords: Logger Logging Log
Platform: UNKNOWN
Classifier: Development Status :: 4 - Beta
Classifier: Intended Audience :: Developers
Classifier: Topic :: Software Development :: Build Tools
Classifier: License :: OSI Approved :: MIT License
Classifier: Programming Language :: Python :: 2.7
Requires-Dist: pymongo
Requires-Dist: packaging (==16.8)
Provides-Extra: dev
Requires-Dist: check-manifest ; extra == 'dev'
Provides-Extra: test
Requires-Dist: coverage ; extra == 'test'
